{
  "properties": {
    "activities": [
      {
        "name": "Notebook2",
        "type": "TridentNotebook",
        "dependsOn": [],
        "policy": {
          "timeout": "12:00:00",
          "retry": 0,
          "retryIntervalInSeconds": 30,
          "secureOutput": false,
          "secureInput": false
        },
        "typeProperties": {
          "notebookId": "14d71ce5-73bf-4a6f-8aab-b1e347b02fe1",
          "workspaceId": "9a2e0242-f493-45f6-996a-79356568d242"
        }
      },
      {
        "name": "Success mail 2",
        "type": "Office365Outlook",
        "dependsOn": [
          {
            "activity": "Notebook2",
            "dependencyConditions": [
              "Succeeded"
            ]
          }
        ],
        "typeProperties": {
          "inputs": {
            "method": "post",
            "path": "/v2/Mail",
            "body": {
              "To": "tringuyen.uit@gmail.com",
              "Subject": "BigQuery to Firestore success",
              "Body": "<p>Success</p>",
              "Sensitivity": "",
              "Importance": "Normal"
            }
          }
        }
      },
      {
        "name": "Failure mail 2",
        "type": "Office365Outlook",
        "dependsOn": [
          {
            "activity": "Notebook2",
            "dependencyConditions": [
              "Failed"
            ]
          }
        ],
        "typeProperties": {
          "inputs": {
            "method": "post",
            "path": "/v2/Mail",
            "body": {
              "To": "tringuyen.uit@gmail.com",
              "Subject": "BigQuery to Firestore fail",
              "Body": "<p>Fail</p>",
              "Sensitivity": "",
              "Importance": "Normal"
            }
          }
        }
      }
    ],
    "logicAppsConnectionPayload": {
      "id": "/subscriptions/21a65d72-f28d-43d4-80e7-d04e41ec025c/resourceGroups/connections-9a2e0242-f493-45f6-996a-79356568d242/providers/Microsoft.Web/connections/1_d4dab9ae-a2e1-487f-9937-82c021be23fb_5aeeca7e-6b43-4408-9e6e-5d0ff256d3ef",
      "properties": {
        "api": {
          "name": "office365",
          "id": "/subscriptions/21a65d72-f28d-43d4-80e7-d04e41ec025c/providers/Microsoft.Web/locations/southeastasia/managedApis/office365"
        }
      }
    }
  }
}